cyzutils/__init__.py
cyzutils/run_py.py
cyzutils/send_mail.py
cyzutils-0.0.5.dist-info/METADATA
cyzutils-0.0.5.dist-info/WHEEL
cyzutils-0.0.5.dist-info/top_level.txt
cyzutils-0.0.5.dist-info/RECORD
