Metadata-Version: 2.1
Name: cyzutils
Version: 0.0.5
Summary: my utils
Home-page: https://github.com/cyz020403
Author: cyz020403
Author-email: cyz020403@gmail.com
License: MIT
Requires-Python: >=3.6
